Workbook

Sheet RESIDENTS
A1: ID | B1: Resident Name | C1: Property | D1: Bed Code | E1: Move-In Date | F1: Move-Out Date | G1: Status | H1: Monthly Rent (₹) | I1: Deposit Paid | J1: Deposit Amt (₹) | K1: Notice Given
A2: R01 | B2: Ananya Roy | C2: Koramangala | D2: K-101 | E2: 45658 | F2: 45747 | G2: Moved Out | H2: 12000 | I2: Yes | J2: 24000 | K2: Yes
A3: R02 | B3: RAHUL MEHTA | C3: Whitefield | D3: W-204 | E3: 45672 | G3: Active | H3: 9500 | I3: Yes | J3: 19000 | K3: No
A4: R03 | B4: priya nair | C4: Koramangala | D4: K-101 | E4: 10/01/2025 ← Same bed as R01, dates overlap | F4: 45777 | G4: Active | H4: 12000 | I4: No | J4: 0 | K4: No
A5: R04 | B5: Vikram Sinha | C5: HSR Layout | D5: H-302 | E5: 45689 | F5: 45716 | G5: Active ← Move-out date has passed | H5: 11000 | I5: Yes | J5: 22000 | K5: Yes
A6: R05 | B6: fatima sheikh | C6: Whitefield | D6: W-107 | E6: 45708 | G6: Active | H6: 7,500 ← Below min ₹8,000 | I6: Yes | J6: 15000 | K6: No
A7: R06 | B7: Arun Pillai | C7: Indiranagar | D7: I-210 | E7: 45717 | G7: Active | H7: 10500 | I7: No | J7: 0 | K7: No
A8: R07 | B8: Meena Iyer | C8: HSR Layout | D8: H-108 | E8: 45721 | G8: Active | H8: 11000 | I8: Yes | J8: 22000 | K8: No
A9: R08 | B9: Dev Shah | C9: Koramangala | D9: K-205 | E9: 45726 | F9: 45721 | G9: Moved Out ← Move-out before move-in | H9: 12000 | I9: Yes | J9: 24000 | K9: Yes
A10: R09 | B10: Zara Khan | C10: Indiranagar | D10: I-210 | E10: 45731 | G10: Active ← Same bed as R06, no end date on R06 | H10: 10500 | I10: Yes | J10: 21000 | K10: No
A11: R10 | B11: Nikhil Gupta | C11: Whitefield | D11: W-310 | E11: 45748 | G11: Active | H11: 9500 | I11: No | J11: 0 | K11: No
A12: R11 | B12: Leela Thomas | C12: HSR Layout | D12: H-215 | E12: 45748 | G12: Active | H12: 11000 | I12: Yes | J12: 11000 | K12: No ← Deposit amount = 1 month only, should be 2
A13: R12 | B13: Sanjay Tiwari | C13: Koramangala | D13: K-308 | E13: 45762 | G13: Active | H13: 12000 | I13: Yes | J13: 24000 | K13: No
A14: R13 | B14: kavya reddy | C14: Indiranagar | D14: I-114 | E14: 45778 | G14: Active | H14: 10500 | I14: Yes | J14: 21000 | K14: No
A15: R14 | B15: Omar Sheikh | C15: Whitefield | D15: W-204 | E15: 45787 | G15: Active ← Same bed as R02, no end date on R02 | H15: 9500 | I15: No | J15: 0 | K15: No
A16: R15 | B16: Tanvi Desai | C16: HSR Layout | D16: H-302 | E16: 45809 | G16: Active | H16: 11000 | I16: Yes | J16: 22000 | K16: No
B19: Red rows contain data errors - see RESIDENTS_CLEAN and ERROR_LOG tabs

Sheet RESIDENTS_CLEAN
A1: ID | B1: Resident Name | C1: Property | D1: Bed Code | E1: Move-In Date | F1: Move-Out Date | G1: Status | H1: Monthly Rent | I1: Deposit Paid | J1: Deposit Amt (₹) | K1: Notice Given | L1: Notes/Flags | M1: Correct Deposit | N1: Deposit Gap
A2: R01 | B2: Ananya Roy | C2: Koramangala | D2: K-101 | E2: 45658 | F2: 45747 | G2: Moved-out | H2: 12000 | I2: Yes | J2: 24000 | K2: Yes | M2: =RESIDENT_CLEAN[[#This Row],[Monthly Rent]]*2 -> 24000 | N2: =IF(I2="No",M2,IF(J2<M2,M2-J2,0)) -> 0
A3: R02 | B3: Rahul Mehta | C3: Whitefield | D3: W-204 | E3: 45672 | G3: Active | H3: 9500 | I3: Yes | J3: 19000 | K3: No | L3: Name Standlized Title Case | M3: =RESIDENT_CLEAN[[#This Row],[Monthly Rent]]*2 -> 19000 | N3: =IF(I3="No",M3,IF(J3<M3,M3-J3,0)) -> 0
A4: R03 | B4: Priya Nair | C4: Koramangala | D4: K-101 | E4: 45667 | F4: 45777 | G4: Moved-out | H4: 12000 | I4: No | J4: 0 | K4: No | L4: Bed Conflit with R01 and Occuping same time/dates flagged for operations | M4: =RESIDENT_CLEAN[[#This Row],[Monthly Rent]]*2 -> 24000 | N4: =IF(I4="No",M4,IF(J4<M4,M4-J4,0)) -> 24000
A5: R04 | B5: Vikram Sinha | C5: HSR Layout | D5: H-302 | E5: 45689 | F5: 45716 | G5: Moved-out | H5: 11000 | I5: Yes | J5: 22000 | K5: Yes | L5: Status corrected Move out date 28/02/2025 alredy passed | M5: =RESIDENT_CLEAN[[#This Row],[Monthly Rent]]*2 -> 22000 | N5: =IF(I5="No",M5,IF(J5<M5,M5-J5,0)) -> 0
A6: R05 | B6: Fatima Sheikh | C6: Whitefield | D6: W-107 | E6: 45708 | G6: Active | H6: 8000 | I6: Yes | J6: 16000 | K6: No | L6: Rent corrected ₹7,500→₹8,000 (below policy min). Deposit updated to 2 months. | M6: =RESIDENT_CLEAN[[#This Row],[Monthly Rent]]*2 -> 16000 | N6: =IF(I6="No",M6,IF(J6<M6,M6-J6,0)) -> 0
A7: R06 | B7: Arun Pillai | C7: Indiranagar | D7: I-210 | E7: 45717 | G7: Active | H7: 10500 | I7: No | J7: 0 | K7: No | M7: =RESIDENT_CLEAN[[#This Row],[Monthly Rent]]*2 -> 21000 | N7: =IF(I7="No",M7,IF(J7<M7,M7-J7,0)) -> 21000
A8: R07 | B8: Meena Iyer | C8: HSR Layout | D8: H-108 | E8: 45721 | G8: Active | H8: 11000 | I8: Yes | J8: 22000 | K8: No | M8: =RESIDENT_CLEAN[[#This Row],[Monthly Rent]]*2 -> 22000 | N8: =IF(I8="No",M8,IF(J8<M8,M8-J8,0)) -> 0
A9: R08 | B9: Dev Shah | C9: Koramangala | D9: K-205 | E9: 45726 | F9: 45721 | G9: Moved-out | H9: 12000 | I9: Yes | J9: 24000 | K9: Yes | L9: Date error move-out 05/03/2025 is before move-in 10/03/2025 flagged for verification with op | M9: =RESIDENT_CLEAN[[#This Row],[Monthly Rent]]*2 -> 24000 | N9: =IF(I9="No",M9,IF(J9<M9,M9-J9,0)) -> 0
A10: R09 | B10: Zara Khan | C10: Indiranagar | D10: I-210 | E10: 45731 | G10: Active | H10: 10500 | I10: Yes | J10: 21000 | K10: No | L10: Bed conflict with R06 (I-210) R06 has no move-out date. Flagged for ops. | M10: =RESIDENT_CLEAN[[#This Row],[Monthly Rent]]*2 -> 21000 | N10: =IF(I10="No",M10,IF(J10<M10,M10-J10,0)) -> 0
A11: R10 | B11: Nikhil Gupta | C11: Whitefield | D11: W-310 | E11: 45748 | G11: Active | H11: 9500 | I11: No | J11: 0 | K11: No | M11: =RESIDENT_CLEAN[[#This Row],[Monthly Rent]]*2 -> 19000 | N11: =IF(I11="No",M11,IF(J11<M11,M11-J11,0)) -> 19000
A12: R11 | B12: Leela Thomas | C12: HSR Layout | D12: H-215 | E12: 45748 | G12: Active | H12: 11000 | I12: Yes | J12: 11000 | K12: No | L12: Deposit corrected should be ₹11000 to ₹22000 Rupee for 2 Month | M12: =RESIDENT_CLEAN[[#This Row],[Monthly Rent]]*2 -> 22000 | N12: =IF(I12="No",M12,IF(J12<M12,M12-J12,0)) -> 11000
A13: R12 | B13: Sanjay Tiwari | C13: Koramangala | D13: K-308 | E13: 45762 | G13: Active | H13: 12000 | I13: Yes | J13: 24000 | K13: No | M13: =RESIDENT_CLEAN[[#This Row],[Monthly Rent]]*2 -> 24000 | N13: =IF(I13="No",M13,IF(J13<M13,M13-J13,0)) -> 0
A14: R13 | B14: Kavya Reddy | C14: Indiranagar | D14: I-114 | E14: 45778 | G14: Active | H14: 10500 | I14: Yes | J14: 21000 | K14: No | L14: Name Standlized Title Case | M14: =RESIDENT_CLEAN[[#This Row],[Monthly Rent]]*2 -> 21000 | N14: =IF(I14="No",M14,IF(J14<M14,M14-J14,0)) -> 0
A15: R14 | B15: Omar Sheikh | C15: Whitefield | D15: W-204 | E15: 45787 | G15: Active | H15: 9500 | I15: No | J15: 0 | K15: No | L15: Bed Conflit with R02 , R02 has no Move out date for W204 Bed Flagged for ops | M15: =RESIDENT_CLEAN[[#This Row],[Monthly Rent]]*2 -> 19000 | N15: =IF(I15="No",M15,IF(J15<M15,M15-J15,0)) -> 19000
A16: R15 | B16: Tanvi Desai | C16: HSR Layout | D16: H-302 | E16: 45809 | G16: Active | H16: 11000 | I16: Yes | J16: 22000 | K16: No | M16: =RESIDENT_CLEAN[[#This Row],[Monthly Rent]]*2 -> 22000 | N16: =IF(I16="No",M16,IF(J16<M16,M16-J16,0)) -> 0
A17: Total | G17: =SUBTOTAL(103,RESIDENT_CLEAN[Status]) -> 15 | H17: =SUBTOTAL(109,RESIDENT_CLEAN[Monthly Rent]) -> 160000 | M17: =SUBTOTAL(109,RESIDENT_CLEAN[Correct Deposit]) -> 320000 | N17: =SUBTOTAL(109,RESIDENT_CLEAN[Deposit Gap]) -> 94000

Sheet PAYMENTS
A1: Payment ID | B1: Resident ID | C1: Month | D1: Amount Due (₹) | E1: Amount Paid (₹) | F1: Payment Date | G1: Mode | H1: Status | I1: Property | J1: Shortfall ₹ | K1: Status2
A2: P001 | B2: R01 | C2: 45658 | D2: 12000 | E2: 12000 | F2: 45660 | G2: UPI | H2: Cleared | I2: =VLOOKUP(PAYMENTS[[#This Row],[Resident ID]],RESIDENT_CLEAN[[#Headers],[#Data]],3,FALSE) -> Koramangala | J2: =PAYMENTS[[#This Row],[Amount Due (₹)]]-PAYMENTS[[#This Row],[Amount Paid (₹)]] -> 0 | K2: =VLOOKUP(PAYMENTS[[#This Row],[Resident ID]],RESIDENT_CLEAN[#All],7,TRUE) -> Moved-out
A3: P002 | B3: R02 | C3: 45658 | D3: 9500 | E3: 9500 | F3: 45662 | G3: Bank Transfer | H3: Cleared | I3: =VLOOKUP(PAYMENTS[[#This Row],[Resident ID]],RESIDENT_CLEAN[[#Headers],[#Data]],3,FALSE) -> Whitefield | J3: =PAYMENTS[[#This Row],[Amount Due (₹)]]-PAYMENTS[[#This Row],[Amount Paid (₹)]] -> 0 | K3: =VLOOKUP(PAYMENTS[[#This Row],[Resident ID]],RESIDENT_CLEAN[#All],7,TRUE) -> Active
A4: P003 | B4: R03 | C4: 45658 | D4: 12000 | E4: 6000 | F4: 45667 | G4: Cash | H4: Partial | I4: =VLOOKUP(PAYMENTS[[#This Row],[Resident ID]],RESIDENT_CLEAN[[#Headers],[#Data]],3,FALSE) -> Koramangala | J4: =PAYMENTS[[#This Row],[Amount Due (₹)]]-PAYMENTS[[#This Row],[Amount Paid (₹)]] -> 6000 | K4: =VLOOKUP(PAYMENTS[[#This Row],[Resident ID]],RESIDENT_CLEAN[#All],7,TRUE) -> Moved-out
A5: P004 | B5: R04 | C5: 45689 | D5: 11000 | E5: 0 | H5: Unpaid | I5: =VLOOKUP(PAYMENTS[[#This Row],[Resident ID]],RESIDENT_CLEAN[[#Headers],[#Data]],3,FALSE) -> HSR Layout | J5: =PAYMENTS[[#This Row],[Amount Due (₹)]]-PAYMENTS[[#This Row],[Amount Paid (₹)]] -> 11000 | K5: =VLOOKUP(PAYMENTS[[#This Row],[Resident ID]],RESIDENT_CLEAN[#All],7,TRUE) -> Moved-out
A6: P005 | B6: R05 | C6: 45689 | D6: 7500 | E6: 7500 | F6: 45690 | G6: UPI | H6: Cleared | I6: =VLOOKUP(PAYMENTS[[#This Row],[Resident ID]],RESIDENT_CLEAN[[#Headers],[#Data]],3,FALSE) -> Whitefield | J6: =PAYMENTS[[#This Row],[Amount Due (₹)]]-PAYMENTS[[#This Row],[Amount Paid (₹)]] -> 0 | K6: =VLOOKUP(PAYMENTS[[#This Row],[Resident ID]],RESIDENT_CLEAN[#All],7,TRUE) -> Active
A7: P006 | B7: R06 | C7: 45717 | D7: 10500 | E7: 10500 | F7: 45717 | G7: UPI | H7: Cleared | I7: =VLOOKUP(PAYMENTS[[#This Row],[Resident ID]],RESIDENT_CLEAN[[#Headers],[#Data]],3,FALSE) -> Indiranagar | J7: =PAYMENTS[[#This Row],[Amount Due (₹)]]-PAYMENTS[[#This Row],[Amount Paid (₹)]] -> 0 | K7: =VLOOKUP(PAYMENTS[[#This Row],[Resident ID]],RESIDENT_CLEAN[#All],7,TRUE) -> Active
A8: P007 | B8: R07 | C8: 45717 | D8: 11000 | E8: 11000 | F8: 45720 | G8: Bank Transfer | H8: Cleared | I8: =VLOOKUP(PAYMENTS[[#This Row],[Resident ID]],RESIDENT_CLEAN[[#Headers],[#Data]],3,FALSE) -> HSR Layout | J8: =PAYMENTS[[#This Row],[Amount Due (₹)]]-PAYMENTS[[#This Row],[Amount Paid (₹)]] -> 0 | K8: =VLOOKUP(PAYMENTS[[#This Row],[Resident ID]],RESIDENT_CLEAN[#All],7,TRUE) -> Active
A9: P008 | B9: R02 | C9: 45689 | D9: 9500 | E9: 9500 | F9: 45695 | G9: UPI | H9: Cleared | I9: =VLOOKUP(PAYMENTS[[#This Row],[Resident ID]],RESIDENT_CLEAN[[#Headers],[#Data]],3,FALSE) -> Whitefield | J9: =PAYMENTS[[#This Row],[Amount Due (₹)]]-PAYMENTS[[#This Row],[Amount Paid (₹)]] -> 0 | K9: =VLOOKUP(PAYMENTS[[#This Row],[Resident ID]],RESIDENT_CLEAN[#All],7,TRUE) -> Active
A10: P009 | B10: R08 | C10: 45717 | D10: 12000 | E10: 12000 | F10: 45726 | G10: Cash | H10: Cleared | I10: =VLOOKUP(PAYMENTS[[#This Row],[Resident ID]],RESIDENT_CLEAN[[#Headers],[#Data]],3,FALSE) -> Koramangala | J10: =PAYMENTS[[#This Row],[Amount Due (₹)]]-PAYMENTS[[#This Row],[Amount Paid (₹)]] -> 0 | K10: =VLOOKUP(PAYMENTS[[#This Row],[Resident ID]],RESIDENT_CLEAN[#All],7,TRUE) -> Moved-out
A11: P010 | B11: R09 | C11: 45717 | D11: 10500 | E11: 0 | H11: Unpaid | I11: =VLOOKUP(PAYMENTS[[#This Row],[Resident ID]],RESIDENT_CLEAN[[#Headers],[#Data]],3,FALSE) -> Indiranagar | J11: =PAYMENTS[[#This Row],[Amount Due (₹)]]-PAYMENTS[[#This Row],[Amount Paid (₹)]] -> 10500 | K11: =VLOOKUP(PAYMENTS[[#This Row],[Resident ID]],RESIDENT_CLEAN[#All],7,TRUE) -> Active
A12: P011 | B12: R10 | C12: 45748 | D12: 9500 | E12: 9500 | F12: 45749 | G12: UPI | H12: Cleared | I12: =VLOOKUP(PAYMENTS[[#This Row],[Resident ID]],RESIDENT_CLEAN[[#Headers],[#Data]],3,FALSE) -> Whitefield | J12: =PAYMENTS[[#This Row],[Amount Due (₹)]]-PAYMENTS[[#This Row],[Amount Paid (₹)]] -> 0 | K12: =VLOOKUP(PAYMENTS[[#This Row],[Resident ID]],RESIDENT_CLEAN[#All],7,TRUE) -> Active
A13: P012 | B13: R11 | C13: 45748 | D13: 11000 | E13: 11000 | F13: 45752 | G13: Bank Transfer | H13: Cleared | I13: =VLOOKUP(PAYMENTS[[#This Row],[Resident ID]],RESIDENT_CLEAN[[#Headers],[#Data]],3,FALSE) -> HSR Layout | J13: =PAYMENTS[[#This Row],[Amount Due (₹)]]-PAYMENTS[[#This Row],[Amount Paid (₹)]] -> 0 | K13: =VLOOKUP(PAYMENTS[[#This Row],[Resident ID]],RESIDENT_CLEAN[#All],7,TRUE) -> Active
A14: P013 | B14: R12 | C14: 45748 | D14: 12000 | E14: 12000 | F14: 45750 | G14: UPI | H14: Cleared | I14: =VLOOKUP(PAYMENTS[[#This Row],[Resident ID]],RESIDENT_CLEAN[[#Headers],[#Data]],3,FALSE) -> Koramangala | J14: =PAYMENTS[[#This Row],[Amount Due (₹)]]-PAYMENTS[[#This Row],[Amount Paid (₹)]] -> 0 | K14: =VLOOKUP(PAYMENTS[[#This Row],[Resident ID]],RESIDENT_CLEAN[#All],7,TRUE) -> Active
A15: P014 | B15: R05 | C15: 45717 | D15: 7500 | E15: 7500 | F15: 45719 | G15: UPI | H15: Cleared | I15: =VLOOKUP(PAYMENTS[[#This Row],[Resident ID]],RESIDENT_CLEAN[[#Headers],[#Data]],3,FALSE) -> Whitefield | J15: =PAYMENTS[[#This Row],[Amount Due (₹)]]-PAYMENTS[[#This Row],[Amount Paid (₹)]] -> 0 | K15: =VLOOKUP(PAYMENTS[[#This Row],[Resident ID]],RESIDENT_CLEAN[#All],7,TRUE) -> Active
A16: P015 | B16: R13 | C16: 45778 | D16: 10500 | E16: 0 | H16: Unpaid | I16: =VLOOKUP(PAYMENTS[[#This Row],[Resident ID]],RESIDENT_CLEAN[[#Headers],[#Data]],3,FALSE) -> Indiranagar | J16: =PAYMENTS[[#This Row],[Amount Due (₹)]]-PAYMENTS[[#This Row],[Amount Paid (₹)]] -> 10500 | K16: =VLOOKUP(PAYMENTS[[#This Row],[Resident ID]],RESIDENT_CLEAN[#All],7,TRUE) -> Active
A17: P016 | B17: R06 | C17: 45748 | D17: 10500 | E17: 5000 | F17: 45755 | G17: Cash | H17: Partial | I17: =VLOOKUP(PAYMENTS[[#This Row],[Resident ID]],RESIDENT_CLEAN[[#Headers],[#Data]],3,FALSE) -> Indiranagar | J17: =PAYMENTS[[#This Row],[Amount Due (₹)]]-PAYMENTS[[#This Row],[Amount Paid (₹)]] -> 5500 | K17: =VLOOKUP(PAYMENTS[[#This Row],[Resident ID]],RESIDENT_CLEAN[#All],7,TRUE) -> Active
A18: P017 | B18: R14 | C18: 45778 | D18: 9500 | E18: 9500 | F18: 45781 | G18: UPI | H18: Cleared | I18: =VLOOKUP(PAYMENTS[[#This Row],[Resident ID]],RESIDENT_CLEAN[[#Headers],[#Data]],3,FALSE) -> Whitefield | J18: =PAYMENTS[[#This Row],[Amount Due (₹)]]-PAYMENTS[[#This Row],[Amount Paid (₹)]] -> 0 | K18: =VLOOKUP(PAYMENTS[[#This Row],[Resident ID]],RESIDENT_CLEAN[#All],7,TRUE) -> Active
A19: P018 | B19: R15 | C19: 45809 | D19: 11000 | E19: 0 | H19: Unpaid | I19: =VLOOKUP(PAYMENTS[[#This Row],[Resident ID]],RESIDENT_CLEAN[[#Headers],[#Data]],3,FALSE) -> HSR Layout | J19: =PAYMENTS[[#This Row],[Amount Due (₹)]]-PAYMENTS[[#This Row],[Amount Paid (₹)]] -> 11000 | K19: =VLOOKUP(PAYMENTS[[#This Row],[Resident ID]],RESIDENT_CLEAN[#All],7,TRUE) -> Active
A20: P019 | B20: R03 | C20: 45689 | D20: 12000 | E20: 12000 | F20: 45694 | G20: UPI | H20: Cleared | I20: =VLOOKUP(PAYMENTS[[#This Row],[Resident ID]],RESIDENT_CLEAN[[#Headers],[#Data]],3,FALSE) -> Koramangala | J20: =PAYMENTS[[#This Row],[Amount Due (₹)]]-PAYMENTS[[#This Row],[Amount Paid (₹)]] -> 0 | K20: =VLOOKUP(PAYMENTS[[#This Row],[Resident ID]],RESIDENT_CLEAN[#All],7,TRUE) -> Moved-out
A21: P020 | B21: R04 | C21: 45717 | D21: 11000 | E21: 11000 | F21: 45721 | G21: Bank Transfer | H21: Cleared | I21: =VLOOKUP(PAYMENTS[[#This Row],[Resident ID]],RESIDENT_CLEAN[[#Headers],[#Data]],3,FALSE) -> HSR Layout | J21: =PAYMENTS[[#This Row],[Amount Due (₹)]]-PAYMENTS[[#This Row],[Amount Paid (₹)]] -> 0 | K21: =VLOOKUP(PAYMENTS[[#This Row],[Resident ID]],RESIDENT_CLEAN[#All],7,TRUE) -> Moved-out
A22: Total | D22: =SUBTOTAL(109,PAYMENTS[Amount Due (₹)]) -> 210000 | E22: =SUBTOTAL(109,PAYMENTS[Amount Paid (₹)]) -> 155500 | J22: =SUBTOTAL(109,PAYMENTS[Shortfall ₹]) -> 54500
H24: =SUMIFS(PAYMENTS[Amount Paid (₹)],PAYMENTS[Status],"Cleared",PAYMENTS[Status],"Partial") -> 0

Sheet TICKETS
A1: Ticket ID | B1: Property | C1: Bed / Area | D1: Issue | E1: Priority | F1: Raised On | G1: Resolved On | H1: Status | I1: Raised By | J1: Tickets Days open | K1: Aging Bucket
A2: T01 | B2: Koramangala | C2: K-101 | D2: Water leakage from ceiling | E2: High | F2: 45718 | G2: 45726 | H2: Resolved | I2: Ananya Roy | J2: =IF(H2="Resolved",IF(G2="",0,G2-F2),DATE(2025,6,20)-F2) -> 8 | K2: =IF(H2="Resolved","Resolved",IF(J2>30,"Critical",IF(J2>14,"Overdue",IF(J2>7,"Needs Follow Up","On Track")))) -> Resolved
A3: T02 | B3: Whitefield | C3: Common | D3: Wi-Fi router not working | E3: Medium | F3: 45731 | H3: Open | I3: Rahul Mehta | J3: =IF(H3="Resolved",IF(G3="",0,G3-F3),DATE(2025,6,20)-F3) -> 97 | K3: =IF(H3="Resolved","Resolved",IF(J3>30,"Critical",IF(J3>14,"Overdue",IF(J3>7,"Needs Follow Up","On Track")))) -> Critical
A4: T03 | B4: HSR Layout | C4: H-302 | D4: Broken wardrobe door | E4: Low | F4: 45736 | H4: Open | I4: Vikram Sinha | J4: =IF(H4="Resolved",IF(G4="",0,G4-F4),DATE(2025,6,20)-F4) -> 92 | K4: =IF(H4="Resolved","Resolved",IF(J4>30,"Critical",IF(J4>14,"Overdue",IF(J4>7,"Needs Follow Up","On Track")))) -> Critical
A5: T04 | B5: Indiranagar | C5: I-210 | D5: AC not cooling | E5: High | F5: 45748 | G5: 45750 | H5: Resolved | I5: Arun Pillai | J5: =IF(H5="Resolved",IF(G5="",0,G5-F5),DATE(2025,6,20)-F5) -> 2 | K5: =IF(H5="Resolved","Resolved",IF(J5>30,"Critical",IF(J5>14,"Overdue",IF(J5>7,"Needs Follow Up","On Track")))) -> Resolved
A6: T05 | B6: Koramangala | C6: K-205 | D6: Bathroom flush broken | E6: High | F6: 45752 | H6: Open | I6: Dev Shah | J6: =IF(H6="Resolved",IF(G6="",0,G6-F6),DATE(2025,6,20)-F6) -> 76 | K6: =IF(H6="Resolved","Resolved",IF(J6>30,"Critical",IF(J6>14,"Overdue",IF(J6>7,"Needs Follow Up","On Track")))) -> Critical
A7: T06 | B7: Whitefield | C7: W-107 | D7: Mould on bathroom wall | E7: Critical | F7: 45757 | H7: Open | I7: Fatima Sheikh | J7: =IF(H7="Resolved",IF(G7="",0,G7-F7),DATE(2025,6,20)-F7) -> 71 | K7: =IF(H7="Resolved","Resolved",IF(J7>30,"Critical",IF(J7>14,"Overdue",IF(J7>7,"Needs Follow Up","On Track")))) -> Critical
A8: T07 | B8: HSR Layout | C8: Common | D8: Hot water not available | E8: High | F8: 45762 | G8: 45765 | H8: Resolved | I8: Meena Iyer | J8: =IF(H8="Resolved",IF(G8="",0,G8-F8),DATE(2025,6,20)-F8) -> 3 | K8: =IF(H8="Resolved","Resolved",IF(J8>30,"Critical",IF(J8>14,"Overdue",IF(J8>7,"Needs Follow Up","On Track")))) -> Resolved
A9: T08 | B9: Indiranagar | C9: I-114 | D9: Main door lock faulty | E9: Critical | F9: 45778 | H9: Open | I9: Kavya Reddy | J9: =IF(H9="Resolved",IF(G9="",0,G9-F9),DATE(2025,6,20)-F9) -> 50 | K9: =IF(H9="Resolved","Resolved",IF(J9>30,"Critical",IF(J9>14,"Overdue",IF(J9>7,"Needs Follow Up","On Track")))) -> Critical
A10: T09 | B10: Koramangala | C10: K-308 | D10: Electricity tripping | E10: High | F10: 45787 | H10: Open | I10: Sanjay Tiwari | J10: =IF(H10="Resolved",IF(G10="",0,G10-F10),DATE(2025,6,20)-F10) -> 41 | K10: =IF(H10="Resolved","Resolved",IF(J10>30,"Critical",IF(J10>14,"Overdue",IF(J10>7,"Needs Follow Up","On Track")))) -> Critical
A11: T10 | B11: Whitefield | C11: W-310 | D11: Geyser not working | E11: Medium | F11: 45789 | G11: 45797 | H11: Resolved | I11: Nikhil Gupta | J11: =IF(H11="Resolved",IF(G11="",0,G11-F11),DATE(2025,6,20)-F11) -> 8 | K11: =IF(H11="Resolved","Resolved",IF(J11>30,"Critical",IF(J11>14,"Overdue",IF(J11>7,"Needs Follow Up","On Track")))) -> Resolved
A12: T11 | B12: HSR Layout | C12: H-215 | D12: Pest infestation in kitchen | E12: High | F12: 45797 | H12: Open | I12: Leela Thomas | J12: =IF(H12="Resolved",IF(G12="",0,G12-F12),DATE(2025,6,20)-F12) -> 31 | K12: =IF(H12="Resolved","Resolved",IF(J12>30,"Critical",IF(J12>14,"Overdue",IF(J12>7,"Needs Follow Up","On Track")))) -> Critical
A13: T12 | B13: Indiranagar | C13: Common | D13: CCTV camera offline | E13: Medium | F13: 45802 | H13: Open | I13: Zara Khan | J13: =IF(H13="Resolved",IF(G13="",0,G13-F13),DATE(2025,6,20)-F13) -> 26 | K13: =IF(H13="Resolved","Resolved",IF(J13>30,"Critical",IF(J13>14,"Overdue",IF(J13>7,"Needs Follow Up","On Track")))) -> Overdue
A14: T13 | B14: Koramangala | C14: K-101 | D14: Seepage from window | E14: Medium | F14: 45809 | H14: Open | I14: Priya Nair | J14: =IF(H14="Resolved",IF(G14="",0,G14-F14),DATE(2025,6,20)-F14) -> 19 | K14: =IF(H14="Resolved","Resolved",IF(J14>30,"Critical",IF(J14>14,"Overdue",IF(J14>7,"Needs Follow Up","On Track")))) -> Overdue
A15: T14 | B15: Whitefield | C15: W-204 | D15: Cupboard key missing | E15: Low | F15: 45813 | G15: 45815 | H15: Resolved | I15: Omar Sheikh | J15: =IF(H15="Resolved",IF(G15="",0,G15-F15),DATE(2025,6,20)-F15) -> 2 | K15: =IF(H15="Resolved","Resolved",IF(J15>30,"Critical",IF(J15>14,"Overdue",IF(J15>7,"Needs Follow Up","On Track")))) -> Resolved
A16: T15 | B16: HSR Layout | C16: H-108 | D16: Light fitting loose | E16: Low | F16: 45818 | H16: Open | I16: Dev Shah | J16: =IF(H16="Resolved",IF(G16="",0,G16-F16),DATE(2025,6,20)-F16) -> 10 | K16: =IF(H16="Resolved","Resolved",IF(J16>30,"Critical",IF(J16>14,"Overdue",IF(J16>7,"Needs Follow Up","On Track")))) -> Needs Follow Up
E19: Resolved | F19: Medium | G19: Critical Problem Need to look at

Sheet ERROR_LOG
A1: ERROR LOGS - Task 1 | NestSpace Co-Living
A2: ID | B2: Table | C2: Field | D2: What's Wrong | E2: Corrected Value | F2: Business Risk if Not Fixed
A3: R02 | B3: RESIDENTS | C3: Resident Name | D3: Rahul Mehta's name was entered in all caps (RAHUL MEHTA). Standardised to Title Case. | E3: Rahul Mehta | F3: Inconsistent data quality
A4: R03/R01 | B4: RESIDENTS | C4: Name/Bed Code | D4: Name in lowercase. Bed K-101 double booked with R01, dates overlap. Move-out date 30/04/2025 already passed but status still showing Active. | E4: Priya Nair: flag for ops; R01 vacated till 31/03/25 so R03 a different bed OR confirm R01 vacated before R03 moved in made changes in Status of Priya Nair | F4: Two residents assigned same bed and revenue and legal dispute risk, Priya Nair status not updated within 3 days of move-out, violating the policy
A5: R04 | B5: RESIDENTS | C5: Status | D5: Move-out date 28/02/2025 already passed but status still showing Active | E5: Moved Out | F5: Bed H-302 appears occupied, blocks re-letting; lost revenue from vacant bed, deposite refund overdues
A6: R05 | B6: RESIDENTS | C6: Monthly Rent | D6: Rent ₹7,500 is below company minimum ₹8,000. Deposit ₹15,000 is also wrong, should be ₹16,000 | E6: ₹8000 + deposit corrected to ₹16,000 | F6: ₹500/month revenue leakage /non-compliance with pricing policy, invalid deposite
A7: R08 | B7: RESIDENTS | C7: Move-out date | D7: Move-out date 05/03/2025 is before move-in date 10/03/2025. Impossible | E7: Move-Out Date 31/03/2025 (assumed; must be verified with ops) | F7: All tenure/revenue calculations will be wrong; creates data integrity failure across reports
A8: R09/R06 | B8: RESIDENTS | C8: Bed Code/ Status | D8: Bed I-210 assigned to (Arun Pillai) R06 (Active from 01-03-2025, no end date) while (Zara Khan) R09 (Active from 15/03/2025) -simultaneous double booking | E8: Add Move-Out Date to R06 OR reassign R09 to different bed - requires ops verification | F8: Double booking risk and potential resident dispute and revenue confusion
A9: R11 | B9: RESIDENTS | C9: Deposite Amount | D9: Deposit ₹11,000 equals only 1 month rent, policy requires 2 months = ₹22,000 | E9: CorrectedDeposite Amount ₹22000 | F9: Company underprotected if resident defaults ₹11,000 shortfall in security cover
A10: R14/R02 | B10: RESIDENTS | C10: Bed Code/ Status | D10: Bed W-204 assigned to (Omar Sheikh) R14 from 10/05/25 while R02 (Rahul Mehta) is still Active with no move-out date | E10: Flagged for operations - R02 end date must be confirmed | F10: Double booking risk, revenue and leagal risk, Billing confusion
A13: BONUS OBSERVATIONS
A15: ID | B15: Table | C15: Field | D15: What's Wrong | E15: Corrected Value | F15: Business Risk if Not Fixed
A16: B1 | B16: PAYMENTS P005/P014 | C16: Amount Due | D16: P005 and P014 show ₹7,500 as amount due but rent was corrected to ₹8,000. That's ₹500 underpayment per month, ₹1,000 short across both payments. | E16: Correct Amount Due to ₹8,000 in both records | F16: Revenue leakage of ₹1,000 unrecorded, ₹500/month shortfall from active resident
A17: B2 | B17: PAYMENTS P020/R04 | D17: P020 shows ₹11,000 collected from R04 in March 2025 but R04 moved out in February. Payment was taken a month after the resident left | E17: Flag for finance review - likely erroneous charge or advance payment | F17: Incorrect revenue recognition, potential refund liability to R04
A18: B3 | B18: RESIDENTS (R02, R06, R09, R14) | C18: Bed allocation process | D18: Three active double-bookings (K-101, I-210, W-204) in a 15-resident dataset is not a data entry accident - it points to a systemic gap, no bed-availability check before assignment. The ops team is assigning beds without verifying current occupancy. | E18: Recommend implementing bed-booking in the property management system | F18: Double booking, revenue risk, dispute resident and legal risk,

Sheet REVENUE_SUMMARY
A1: REVENUE SUMMARY - Data Audit Task 2| NestSpace Co-living
A2: Property | B2: Total Beds | C2: Active Residents | D2: Occupancy Rate | E2: Total Monthly Rent Collectible | F2: Total Rent Collected | G2: Total Outstanding | H2: Total Gap
A3: Koramangala | B3: 30 | C3: =COUNTIFS(RESIDENT_CLEAN[Property],REVENUE_SUMMARY!A3,RESIDENT_CLEAN[Status],"Active") -> 1 | D3: =Table5[[#This Row],[ Active Residents ]]/Table5[[#This Row],[ Total Beds ]] -> 0.033333333 | E3: =SUMIFS(RESIDENT_CLEAN[Monthly Rent],RESIDENT_CLEAN[Property],Table5[[#This Row],[Property]],RESIDENT_CLEAN[Status],"Active") -> 12000 | F3: =SUMIFS(PAYMENTS[Amount Paid (₹)], PAYMENTS[Property], Table5[[#This Row],[Property]], PAYMENTS[Status], "Cleared") + SUMIFS(PAYMENTS[Amount Paid (₹)], PAYMENTS[Property], Table5[[#This Row],[Property]], PAYMENTS[Status], "Partial") -> 54000 | G3: =SUMIFS(PAYMENTS[Shortfall ₹],PAYMENTS[Property],Table5[[#This Row],[Property]]) -> 6000 | H3: =SUMIF(RESIDENT_CLEAN[Property],Table5[[#This Row],[Property]],RESIDENT_CLEAN[Deposit Gap]) -> 24000
A4: Whitefield | B4: 30 | C4: =COUNTIFS(RESIDENT_CLEAN[Property],REVENUE_SUMMARY!A4,RESIDENT_CLEAN[Status],"Active") -> 4 | D4: =Table5[[#This Row],[ Active Residents ]]/Table5[[#This Row],[ Total Beds ]] -> 0.13333333 | E4: =SUMIFS(RESIDENT_CLEAN[Monthly Rent],RESIDENT_CLEAN[Property],Table5[[#This Row],[Property]],RESIDENT_CLEAN[Status],"Active") -> 36500 | F4: =SUMIFS(PAYMENTS[Amount Paid (₹)], PAYMENTS[Property], Table5[[#This Row],[Property]], PAYMENTS[Status], "Cleared") + SUMIFS(PAYMENTS[Amount Paid (₹)], PAYMENTS[Property], Table5[[#This Row],[Property]], PAYMENTS[Status], "Partial") -> 53000 | G4: =SUMIFS(PAYMENTS[Shortfall ₹],PAYMENTS[Property],Table5[[#This Row],[Property]]) -> 0 | H4: =SUMIF(RESIDENT_CLEAN[Property],Table5[[#This Row],[Property]],RESIDENT_CLEAN[Deposit Gap]) -> 38000
A5: HSR Layout | B5: 30 | C5: =COUNTIFS(RESIDENT_CLEAN[Property],REVENUE_SUMMARY!A5,RESIDENT_CLEAN[Status],"Active") -> 3 | D5: =Table5[[#This Row],[ Active Residents ]]/Table5[[#This Row],[ Total Beds ]] -> 0.1 | E5: =SUMIFS(RESIDENT_CLEAN[Monthly Rent],RESIDENT_CLEAN[Property],Table5[[#This Row],[Property]],RESIDENT_CLEAN[Status],"Active") -> 33000 | F5: =SUMIFS(PAYMENTS[Amount Paid (₹)], PAYMENTS[Property], Table5[[#This Row],[Property]], PAYMENTS[Status], "Cleared") + SUMIFS(PAYMENTS[Amount Paid (₹)], PAYMENTS[Property], Table5[[#This Row],[Property]], PAYMENTS[Status], "Partial") -> 33000 | G5: =SUMIFS(PAYMENTS[Shortfall ₹],PAYMENTS[Property],Table5[[#This Row],[Property]]) -> 22000 | H5: =SUMIF(RESIDENT_CLEAN[Property],Table5[[#This Row],[Property]],RESIDENT_CLEAN[Deposit Gap]) -> 11000
A6: Indiranagar | B6: 30 | C6: =COUNTIFS(RESIDENT_CLEAN[Property],REVENUE_SUMMARY!A6,RESIDENT_CLEAN[Status],"Active") -> 3 | D6: =Table5[[#This Row],[ Active Residents ]]/Table5[[#This Row],[ Total Beds ]] -> 0.1 | E6: =SUMIFS(RESIDENT_CLEAN[Monthly Rent],RESIDENT_CLEAN[Property],Table5[[#This Row],[Property]],RESIDENT_CLEAN[Status],"Active") -> 31500 | F6: =SUMIFS(PAYMENTS[Amount Paid (₹)], PAYMENTS[Property], Table5[[#This Row],[Property]], PAYMENTS[Status], "Cleared") + SUMIFS(PAYMENTS[Amount Paid (₹)], PAYMENTS[Property], Table5[[#This Row],[Property]], PAYMENTS[Status], "Partial") -> 15500 | G6: =SUMIFS(PAYMENTS[Shortfall ₹],PAYMENTS[Property],Table5[[#This Row],[Property]]) -> 26500 | H6: =SUMIF(RESIDENT_CLEAN[Property],Table5[[#This Row],[Property]],RESIDENT_CLEAN[Deposit Gap]) -> 21000
A7: Total | B7: =SUBTOTAL(109,Table5[[ Total Beds ]]) -> 120 | C7: =SUBTOTAL(109,Table5[[ Active Residents ]]) -> 11 | D7: =SUBTOTAL(101,Table5[Occupancy Rate]) -> 0.091666667 | E7: =SUBTOTAL(109,Table5[Total Monthly Rent Collectible]) -> 113000 | F7: =SUBTOTAL(109,Table5[[ Total Rent Collected ]]) -> 155500 | G7: =SUBTOTAL(109,Table5[[ Total Outstanding ]]) -> 54500 | H7: =SUBTOTAL(109,Table5[Total Gap]) -> 94000
A11: WRITTEN ANSWERS - Task 2
A12: 2A - Outstanding Dues
A13: 1. Which property has the highest total outstanding rent? By how much does it lead the second-highest?
A14: Highest outstanding rent & gap | B14: Indiranagar has the highest outstanding rent at ₹26,500 - three residents haven't fully paid (R09, R13, and R06 partial). HSR Layout is second at ₹22,000. Gap between the two is ₹4,500.
A16: 2. There are 2 residents who have made partial payments. What is the total shortfall from those two payments combined?
A17: Partial payment shortfall | B17: Two residents made partial payments - R03 paid ₹6,000 against ₹12,000 due (shortfall ₹6,000), and R06 paid ₹5,000 against ₹10,500 due (shortfall ₹5,500). Total shortfall from both = ₹11,500.
A19: 3.One resident's rent is below the company minimum. If their rent is corrected to ₹8,000 going forward, how much extra monthly revenue does that generate across a 3-month period?
A20: Below-minimum rent correction | B20: R05 Fatima Sheikh's rent was below the minimum at ₹7,500. Correcting it to ₹8,000 gives ₹500 extra per month - over 3 months that's ₹1,500 additional revenue.
A22: 2B - Deposit Health Check
A23: 4. How many residents have NOT paid their deposit? List their names and the total deposit amount outstanding (use the correct 2-month policy amount for each).
A24: Residents with NO deposit paid | B24: Four residents haven't paid any deposit - Priya Nair, Arun Pillai, Nikhil Gupta, and Omar Sheikh - totalling ₹83,000. R11 Leela Thomas paid only ₹11,000 instead of ₹22,000. Total deposit gap across all five residents = ₹94,000.
A25: 5 How many residents have paid a deposit that is LESS than the 2-month policy amount? What is the total gap?
A26: Deposits paid but below 2-month policy | B26: R11 Leela Thomas is the only resident who paid a deposit but came up short she paid ₹11,000 against the required ₹22,000, leaving an ₹11,000 gap. All other residents who paid deposit either met the policy amount exactly or had their deposit corrected.

Sheet SUMMARY
A1: NestSpace Co-Living - Property Health | As of 20 June 2025
B3: PERFORMANCE SNAPSHOT
B4: Total Beds | C4: Active Residents | D4: Overall Occupancy Rate | E4: Monthly Collectible | F4: Rent Collected | G4: Total Outstanding | H4: Deposit Gap | I4: No-Deposit Residents | J4: Collection Efficiency %( money owed was actually collected)
B5: =Table5[[#Totals],[ Total Beds ]] -> 120 | C5: =Table5[[#Totals],[ Active Residents ]] -> 11 | D5: =Table5[[#Totals],[Occupancy Rate]] -> 0.091666667 | E5: =Table5[[#Totals],[Total Monthly Rent Collectible]] -> 113000 | F5: =Table5[[#Totals],[ Total Rent Collected ]] -> 155500 | G5: =Table5[[#Totals],[ Total Outstanding ]] -> 54500 | H5: =Table5[[#Totals],[Total Gap]] -> 94000 | I5: =COUNTIF(RESIDENT_CLEAN[Deposit Paid],"No") -> 4 | J5: =Table5[[#Totals],[ Total Rent Collected ]]/(Table5[[#Totals],[ Total Rent Collected ]]+Table5[[#Totals],[ Total Outstanding ]]) -> 0.74047619
B8: PROPERTY BREAKDOWN (Q1 & Q2 of Dashboard)
B9: Property | C9: Total Beds | D9: Active Residents | E9: Occupancy % | F9: Monthly Collectible (₹) | G9: Rent Collected (₹) | H9: Outstanding (₹) | I9: Deposit Gap (₹) | J9: Open Tickets | K9: Critical/Overdue Tickets
B10: Koramangala | C10: {=Table5[[ Total Beds ]:[Total Gap]]} -> 30 | D10: 1 | E10: 0.033333333 | F10: 12000 | G10: 54000 | H10: 6000 | I10: 24000 | J10: =COUNTIFS(TICKETS[Property],SUMMARY!B10,TICKETS[Status],"Open") -> 3 | K10: 3
B11: Whitefield | C11: 30 | D11: 4 | E11: 0.13333333 | F11: 36500 | G11: 53000 | H11: 0 | I11: 38000 | J11: =COUNTIFS(TICKETS[Property],SUMMARY!B11,TICKETS[Status],"Open") -> 2 | K11: 2
B12: HSR Layout | C12: 30 | D12: 3 | E12: 0.1 | F12: 33000 | G12: 33000 | H12: 22000 | I12: 11000 | J12: =COUNTIFS(TICKETS[Property],SUMMARY!B12,TICKETS[Status],"Open") -> 3 | K12: 2
B13: Indiranagar | C13: 30 | D13: 3 | E13: 0.1 | F13: 31500 | G13: 15500 | H13: 26500 | I13: 21000 | J13: =COUNTIFS(TICKETS[Property],SUMMARY!B13,TICKETS[Status],"Open") -> 2 | K13: 2
B16: MAINTENANCE ANALYSIS - Task 3 Answers
A17: 1 | B17: Which property has the most Critical or Overdue open tickets? How many?
B18: Koramangala has the most with 3 Critical/Overdue tickets - bathroom flush broken (T05, 76 days), electricity tripping (T09, 41 days), and seepage (T13, 19 days). All other properties have 2 each. Worth noting Whitefield has the oldest single ticket in the system - Wi-Fi down for 97 days.
A20: 2 | B20: There are two Critical-priority tickets that have been open for over 30 days. What is the resident risk for each, and what would you recommend?
B21: T06 Whitefield - mould on bathroom wall, 71 days. This is a health hazard and a legal liability, needs a contractor today. T08 Indiranagar - main door lock broken, 50 days. A resident can't secure her own room, that's a direct safety risk. Both should have been actioned weeks ago.
A23: 3 | B23: Write a 4-sentence escalation message to your operations Manager about the maintenance situation. Be specific - name the properties, ticket IDs, and recommended actions.
B24: 1.For site visits this week, I'd suggest starting with Whitefield. The Wi-Fi has been down for 97 days which is frankly embarrassing, the mould needs a physical check beyond just the contractor fix, and there's a bed conflict on W-204 that we need to sort out in person. A lot to fix but one visit covers it all. 2.Indiranagar should be your second stop. Beyond the door lock, we have ₹26,500 in outstanding rent across three residents - that's not a coincidence, something's going on there that a phone call won't fix. 3.Koramangala has the most open tickets right now (3), including electrical tripping which I wouldn't sit on much longer. Aim to get there by end of week. 4. HSR Layout is relatively stable but no outstanding rent but pest infestation in the kitchen (T11) and a wardrobe that's been broken since March (T03) need to get scheduled before residents start complaining more formally.

Sheet DASHBOARD1
A1: NestSpace Co-Living | Property Health Dashboard | As of 20 June 2025
B4: Active Residents | E4: Total Outstanding | H4: Deposit Gap | K4: Collection Efficiency % | N4: A | O4: B
B5: =SUMMARY!C5 -> 11 | E5: =SUMMARY!G5 -> 54500 | H5: =SUMMARY!H5 -> 94000 | K5: =SUMMARY!J5 -> 0.74047619 | N5: Indiranagar | O5: 0.36904762
N6: HSR Layout | O6: 0.6
A7: Property overview | N7: Koramangala | O7: 0.9
N8: Whitefield | O8: 1
B9: Koramangala | E9: Whitefield | H9: HSR Layout | K9: Indiranagar
B10: Occupancy | C10: =SUMMARY!E10 -> 0.033333333 | E10: Occupancy | F10: =SUMMARY!E11 -> 0.13333333 | H10: Occupancy | I10: =SUMMARY!E12 -> 0.1 | K10: Occupancy | L10: =SUMMARY!E13 -> 0.1 | N10: Whitefield | O10: 0
B11: Active Residency | C11: =SUMMARY!D10 -> 1 | E11: Active Residency | F11: =SUMMARY!D11 -> 4 | H11: Active Residency | I11: =SUMMARY!D12 -> 3 | K11: Active Residency | L11: =SUMMARY!D13 -> 3 | N11: Koramangala | O11: 6000
B12: Outstanding | C12: =SUMMARY!H10 -> 6000 | E12: Outstanding | F12: =SUMMARY!H11 -> 0 | H12: Outstanding | I12: =SUMMARY!H12 -> 22000 | K12: Outstanding | L12: =SUMMARY!H13 -> 26500 | N12: HSR Layout | O12: 22000
B13: Deposite Gap | C13: =SUMMARY!I10 -> 24000 | E13: Deposite Gap | F13: =SUMMARY!I11 -> 38000 | H13: Deposite Gap | I13: =SUMMARY!I12 -> 11000 | K13: Deposite Gap | L13: =SUMMARY!I13 -> 21000 | N13: Indiranagar | O13: 26500
B14: Collection | C14: =SUMMARY!G10/(SUMMARY!G10+SUMMARY!H10) -> 0.9 | E14: Collection | F14: =SUMMARY!G11/(SUMMARY!G11+SUMMARY!H11) -> 1 | H14: Collection | I14: =SUMMARY!G12/(SUMMARY!G12+SUMMARY!H12) -> 0.6 | K14: Collection | L14: =SUMMARY!G13/(SUMMARY!G13+SUMMARY!H13) -> 0.36904762
B15: Open Tickets | C15: =SUMMARY!J10 -> 3 | E15: Open Tickets | F15: =SUMMARY!J11 -> 2 | H15: Open Tickets | I15: =SUMMARY!J12 -> 3 | K15: Open Tickets | L15: =SUMMARY!J13 -> 2
B16: Cri/ Overdues | C16: =SUMMARY!K10 -> 3 | E16: Cri/ Overdues | F16: =SUMMARY!K11 -> 2 | H16: Cri/ Overdues | I16: =SUMMARY!K12 -> 2 | K16: Cri/ Overdues | L16: =SUMMARY!K13 -> 2
H18: Open tickets - critical & overdue
H20: Ticket ID | I20: Property | J20: Issue | K20: Tickets Days open | L20: Aging Bucket
H21: T02 | I21: Whitefield | J21: Wi-Fi Down | K21: 97 | L21: Critical
H22: T03 | I22: HSR Layout | J22: Wardrobe | K22: 92 | L22: Critical
H23: T05 | I23: Koramangala | J23: Flush broken | K23: 76 | L23: Critical
H24: T06 | I24: Whitefield | J24: Mould bathroom wall | K24: 71 | L24: Critical
H25: T08 | I25: Indiranagar | J25: door lock | K25: 50 | L25: Critical
H26: T09 | I26: Koramangala | J26: Electricity | K26: 41 | L26: Critical
H27: T11 | I27: HSR Layout | J27: Pest kitchen | K27: 31 | L27: Critical
H28: T12 | I28: Indiranagar | J28: CCTV offline | K28: 26 | L28: Overdue
H29: T13 | I29: Koramangala | J29: Seepage | K29: 19 | L29: Overdue
H30: T15 | I30: HSR Layout | J30: Light loose | K30: 10 | L30: Needs Follow Up
H33: Deposit flags - ₹94,000 total gap
H34: Resident | I34: Property | J34: Total Gap
H35: Priya Nair (R03) | I35: Koramangala | J35: 24000
H36: Arun Pillai (R06) | I36: Indiranagar | J36: 21000
H37: Nikhil Gupta(R10) | I37: Whitefield | J37: 19000
B38: Site visit priority | H38: Omar Sheikh (R14) | I38: Whitefield | J38: 19000
B39: Whitefield | H39: Leela Thomas (R11) | I39: HSR Layout | J39: 11000
B40: Mould (health hazard, 71d) + Wi-Fi (97d) + W-204 bed conflict | H40: Total Gap | J40: =SUM(J35:J39) -> 94000
B42: Indiranagar
B43: ₹26,500 outstanding (3 residents) + door lock (50d) + CCTV offline
B45: Koramangala
B46: 3 tickets including electrical tripping (safety) + ₹6,000 outstanding
B48: HSR Layout
B49: No outstanding rent -but wardrobe (92d) + pest infestation need scheduling
